LazyForecast/LazyForecast.py
LazyForecast/__init__.py
lazyforecast-0.0.1.dist-info/LICENSE
lazyforecast-0.0.1.dist-info/METADATA
lazyforecast-0.0.1.dist-info/WHEEL
lazyforecast-0.0.1.dist-info/top_level.txt
lazyforecast-0.0.1.dist-info/RECORD
